pyaccredible/__init__.py
pyaccredible/client.py
pyaccredible-0.6.0.dist-info/DESCRIPTION.rst
pyaccredible-0.6.0.dist-info/METADATA
pyaccredible-0.6.0.dist-info/RECORD
pyaccredible-0.6.0.dist-info/WHEEL
pyaccredible-0.6.0.dist-info/metadata.json
pyaccredible-0.6.0.dist-info/top_level.txt
