Metadata-Version: 2.0
Name: pyaccredible
Version: 0.6.0
Summary: Python Wrapper Accredible API
Home-page: https://github.com/exolever/pyaccredible
Author: Tomas Garzon
Author-email: tomasgarzonhervas@gmail.com
License: MIT license
Keywords: pyaccredible
Platform: UNKNOWN
Classifier: Development Status :: 2 - Pre-Alpha
Classifier: Intended Audience :: Developers
Classifier: License :: OSI Approved :: MIT License
Classifier: Natural Language :: English
Classifier: Programming Language :: Python :: 2
Classifier: Programming Language :: Python :: 2.7
Classifier: Programming Language :: Python :: 3
Classifier: Programming Language :: Python :: 3.4
Classifier: Programming Language :: Python :: 3.5
Classifier: Programming Language :: Python :: 3.6
Classifier: Programming Language :: Python :: 3.7
